{
  "data": {
    "article": {},
    "attachments": {
      "media_keys": [
        "3_1825908436250537986"
      ],
      "media_source_tweet_id": [
        "1825908453598285919"
      ]
    },
    "author_id": "1738375202168532992",
    "conversation_id": "1826629773361398091",
    "created_at": "2024-08-22T14:37:29.000Z",
    "edit_controls": {
      "editable_until": "2024-08-22T15:37:29.000Z",
      "edits_remaining": 5,
      "is_edit_eligible": false
    },
    "edit_history_tweet_ids": [
      "1826629773361398091"
    ],
    "entities": {
      "mentions": [
        {
          "end": 13,
          "id": "1588581196304642049",
          "start": 3,
          "username": "xuserpost"
        }
      ],
      "urls": [
        {
          "display_url": "pic.x.com/enzzjcnkch",
          "end": 38,
          "expanded_url": "https://twitter.com/xuserpost/status/1825908453598285919/photo/1",
          "media_key": "3_1825908436250537986",
          "start": 15,
          "url": "https://t.co/EnzZjcnKch"
        }
      ]
    },
    "geo": {},
    "id": "1826629773361398091",
    "lang": "zxx",
    "possibly_sensitive": false,
    "public_metrics": {
      "bookmark_count": 0,
      "impression_count": 0,
      "like_count": 0,
      "quote_count": 0,
      "reply_count": 0,
      "retweet_count": 895
    },
    "referenced_tweets": [
      {
        "id": "1825908453598285919",
        "type": "retweeted"
      }
    ],
    "reply_settings": "everyone",
    "text": "RT @xuserpost: https://t.co/EnzZjcnKch"
  },
  "includes": {
    "media": [
      {
        "height": 1315,
        "media_key": "3_1825908436250537986",
        "public_metrics": {},
        "type": "photo",
        "url": "https://pbs.twimg.com/media/GVbuDHcaMAI5PoV.jpg",
        "width": 1580
      }
    ],
    "tweets": [
      {
        "article": {},
        "attachments": {
          "media_keys": [
            "3_1825908436250537986"
          ],
          "media_source_tweet_id": [
            "1825908453598285919"
          ]
        },
        "author_id": "1738375202168532992",
        "conversation_id": "1826629773361398091",
        "created_at": "2024-08-22T14:37:29.000Z",
        "edit_controls": {
          "editable_until": "2024-08-22T15:37:29.000Z",
          "edits_remaining": 5,
          "is_edit_eligible": false
        },
        "edit_history_tweet_ids": [
          "1826629773361398091"
        ],
        "entities": {
          "mentions": [
            {
              "end": 13,
              "id": "1588581196304642049",
              "start": 3,
              "username": "xuserpost"
            }
          ],
          "urls": [
            {
              "display_url": "pic.x.com/enzzjcnkch",
              "end": 38,
              "expanded_url": "https://twitter.com/xuserpost/status/1825908453598285919/photo/1",
              "media_key": "3_1825908436250537986",
              "start": 15,
              "url": "https://t.co/EnzZjcnKch"
            }
          ]
        },
        "geo": {},
        "id": "1826629773361398091",
        "lang": "zxx",
        "possibly_sensitive": false,
        "public_metrics": {
          "bookmark_count": 0,
          "impression_count": 0,
          "like_count": 0,
          "quote_count": 0,
          "reply_count": 0,
          "retweet_count": 895
        },
        "referenced_tweets": [
          {
            "id": "1825908453598285919",
            "type": "retweeted"
          }
        ],
        "reply_settings": "everyone",
        "text": "RT @xuserpost: https://t.co/EnzZjcnKch"
      },
      {
        "article": {},
        "attachments": {
          "media_keys": [
            "3_1825908436250537986"
          ]
        },
        "author_id": "1588581196304642049",
        "conversation_id": "1825908453598285919",
        "created_at": "2024-08-20T14:51:13.000Z",
        "edit_controls": {
          "editable_until": "2024-08-20T15:51:13.000Z",
          "edits_remaining": 5,
          "is_edit_eligible": true
        },
        "edit_history_tweet_ids": [
          "1825908453598285919"
        ],
        "entities": {
          "urls": [
            {
              "display_url": "pic.x.com/enzzjcnkch",
              "end": 23,
              "expanded_url": "https://twitter.com/xuserpost/status/1825908453598285919/photo/1",
              "media_key": "3_1825908436250537986",
              "start": 0,
              "url": "https://t.co/EnzZjcnKch"
            }
          ]
        },
        "geo": {},
        "id": "1825908453598285919",
        "lang": "zxx",
        "possibly_sensitive": false,
        "public_metrics": {
          "bookmark_count": 294,
          "impression_count": 86481,
          "like_count": 4716,
          "quote_count": 8,
          "reply_count": 2,
          "retweet_count": 895
        },
        "reply_settings": "everyone",
        "text": "https://t.co/EnzZjcnKch"
      }
    ],
    "users": [
      {
        "created_at": "2023-12-23T01:45:30.000Z",
        "description": "",
        "id": "1738375202168532992",
        "name": "マルコ",
        "profile_image_url": "https://pbs.twimg.com/profile_images/1756236534519566336/-sTar85R_normal.jpg",
        "protected": false,
        "public_metrics": {
          "followers_count": 6,
          "following_count": 59,
          "like_count": 3031,
          "listed_count": 0,
          "tweet_count": 560
        },
        "username": "Wanzi5450",
        "verified": false
      },
      {
        "created_at": "2022-11-04T17:23:00.000Z",
        "description": "踊ろうぜ!! 夏の夢!! Summer days, play and gaze, sunshine haze!!",
        "id": "1588581196304642049",
        "name": "裄丈",
        "pinned_tweet_id": "1701852270844084598",
        "profile_image_url": "https://pbs.twimg.com/profile_images/1816703258695720960/wVpF8z-x_normal.png",
        "protected": false,
        "public_metrics": {
          "followers_count": 21498,
          "following_count": 37,
          "like_count": 1643,
          "listed_count": 65,
          "tweet_count": 1878
        },
        "username": "xuserpost",
        "verified": false
      }
    ]
  }
}