{
  "data": {
    "article": {},
    "attachments": {},
    "author_id": "1738375202168532992",
    "conversation_id": "2068999950785237144",
    "created_at": "2026-06-23T01:04:59.000Z",
    "edit_controls": {
      "editable_until": "2026-06-23T02:04:59.000Z",
      "edits_remaining": 5,
      "is_edit_eligible": false
    },
    "edit_history_tweet_ids": [
      "2069225170469052854"
    ],
    "entities": {
      "mentions": [
        {
          "end": 15,
          "id": "1903099585129816064",
          "start": 0,
          "username": "tokerumaisurii"
        }
      ]
    },
    "geo": {},
    "id": "2069225170469052854",
    "in_reply_to_user_id": "1903099585129816064",
    "lang": "zh",
    "note_tweet": {
      "entities": {}
    },
    "possibly_sensitive": false,
    "public_metrics": {
      "bookmark_count": 0,
      "impression_count": 0,
      "like_count": 0,
      "quote_count": 0,
      "reply_count": 0,
      "retweet_count": 0
    },
    "referenced_tweets": [
      {
        "id": "2069077926566346781",
        "type": "replied_to"
      }
    ],
    "reply_settings": "everyone",
    "text": "@tokerumaisurii 是的，爸爸很帅气😼"
  },
  "includes": {
    "tweets": [
      {
        "article": {},
        "attachments": {},
        "author_id": "1738375202168532992",
        "conversation_id": "2068999950785237144",
        "created_at": "2026-06-23T01:04:59.000Z",
        "edit_controls": {
          "editable_until": "2026-06-23T02:04:59.000Z",
          "edits_remaining": 5,
          "is_edit_eligible": false
        },
        "edit_history_tweet_ids": [
          "2069225170469052854"
        ],
        "entities": {
          "mentions": [
            {
              "end": 15,
              "id": "1903099585129816064",
              "start": 0,
              "username": "tokerumaisurii"
            }
          ]
        },
        "geo": {},
        "id": "2069225170469052854",
        "in_reply_to_user_id": "1903099585129816064",
        "lang": "zh",
        "note_tweet": {
          "entities": {}
        },
        "possibly_sensitive": false,
        "public_metrics": {
          "bookmark_count": 0,
          "impression_count": 0,
          "like_count": 0,
          "quote_count": 0,
          "reply_count": 0,
          "retweet_count": 0
        },
        "referenced_tweets": [
          {
            "id": "2069077926566346781",
            "type": "replied_to"
          }
        ],
        "reply_settings": "everyone",
        "text": "@tokerumaisurii 是的，爸爸很帅气😼"
      },
      {
        "article": {},
        "attachments": {},
        "author_id": "1903099585129816064",
        "conversation_id": "2068999950785237144",
        "created_at": "2026-06-22T15:19:53.000Z",
        "edit_controls": {
          "editable_until": "2026-06-22T16:19:53.000Z",
          "edits_remaining": 5,
          "is_edit_eligible": false
        },
        "edit_history_tweet_ids": [
          "2069077926566346781"
        ],
        "entities": {
          "mentions": [
            {
              "end": 10,
              "id": "1738375202168532992",
              "start": 0,
              "username": "Wanzi5450"
            }
          ]
        },
        "geo": {},
        "id": "2069077926566346781",
        "in_reply_to_user_id": "1738375202168532992",
        "lang": "zh",
        "note_tweet": {
          "entities": {}
        },
        "possibly_sensitive": false,
        "public_metrics": {
          "bookmark_count": 0,
          "impression_count": 240,
          "like_count": 1,
          "quote_count": 0,
          "reply_count": 1,
          "retweet_count": 0
        },
        "referenced_tweets": [
          {
            "id": "2068999950785237144",
            "type": "replied_to"
          }
        ],
        "reply_settings": "everyone",
        "text": "@Wanzi5450 这个改措辞确实是稳准狠啊"
      }
    ],
    "users": [
      {
        "created_at": "2023-12-23T01:45:30.000Z",
        "description": "叫我丸子就好",
        "id": "1738375202168532992",
        "name": "マルコ",
        "pinned_tweet_id": "2038194838785732817",
        "profile_image_url": "https://pbs.twimg.com/profile_images/2025519980977270784/8ZuZMmmz_normal.jpg",
        "protected": false,
        "public_metrics": {
          "followers_count": 341,
          "following_count": 332,
          "like_count": 20095,
          "listed_count": 0,
          "media_count": 544,
          "tweet_count": 4376
        },
        "url": "",
        "username": "Wanzi5450",
        "verified": false
      },
      {
        "created_at": "2025-03-21T15:01:17.000Z",
        "description": "虚空猫猫鱼 ¦ 我等心友🪼 @VentusUta :: 🎇 @Opiumash :: 🐱 @_rawSalmon ¦ maimai 15006 弱虫モンブラン AP+ FDX アマカミサマ AP+ ¦ https://t.co/2EQB4n1ssZ",
        "entities": {
          "description": {
            "mentions": [
              {
                "end": 24,
                "start": 14,
                "username": "VentusUta"
              },
              {
                "end": 39,
                "start": 30,
                "username": "Opiumash"
              },
              {
                "end": 56,
                "start": 45,
                "username": "_rawSalmon"
              }
            ],
            "urls": [
              {
                "display_url": "ngl.link/c13h16n2.hcl",
                "end": 124,
                "expanded_url": "https://ngl.link/c13h16n2.hcl",
                "start": 101,
                "url": "https://t.co/2EQB4n1ssZ"
              }
            ]
          },
          "url": {
            "urls": [
              {
                "display_url": "networkutopia.com",
                "end": 23,
                "expanded_url": "http://www.networkutopia.com",
                "start": 0,
                "url": "https://t.co/JLTijPr6i9"
              }
            ]
          }
        },
        "id": "1903099585129816064",
        "location": "Ripley's Aquarium of Canada",
        "name": "小虚空🍥",
        "pinned_tweet_id": "2043760871839617199",
        "profile_image_url": "https://pbs.twimg.com/profile_images/2037110980358868993/9NOxcDIU_normal.jpg",
        "protected": false,
        "public_metrics": {
          "followers_count": 4165,
          "following_count": 332,
          "like_count": 118860,
          "listed_count": 14,
          "media_count": 1380,
          "tweet_count": 21046
        },
        "url": "https://t.co/JLTijPr6i9",
        "username": "tokerumaisurii",
        "verified": true
      }
    ]
  }
}