{
  "data": {
    "article": {},
    "attachments": {},
    "author_id": "1738375202168532992",
    "conversation_id": "2067983284316082317",
    "created_at": "2026-06-19T15:06:19.000Z",
    "edit_controls": {
      "editable_until": "2026-06-19T16:06:19.000Z",
      "edits_remaining": 5,
      "is_edit_eligible": false
    },
    "edit_history_tweet_ids": [
      "2067987345509605862"
    ],
    "entities": {
      "mentions": [
        {
          "end": 13,
          "id": "1991795014163382272",
          "start": 0,
          "username": "fortearsidie"
        }
      ]
    },
    "geo": {},
    "id": "2067987345509605862",
    "in_reply_to_user_id": "1991795014163382272",
    "lang": "zh",
    "note_tweet": {
      "entities": {}
    },
    "possibly_sensitive": false,
    "public_metrics": {
      "bookmark_count": 0,
      "impression_count": 0,
      "like_count": 0,
      "quote_count": 0,
      "reply_count": 0,
      "retweet_count": 0
    },
    "referenced_tweets": [
      {
        "id": "2067983284316082317",
        "type": "replied_to"
      }
    ],
    "reply_settings": "everyone",
    "text": "@fortearsidie 哦！！！！我也想去wwww人多吗！"
  },
  "includes": {
    "media": [
      {
        "height": 2048,
        "media_key": "3_2067983255014658048",
        "public_metrics": {},
        "type": "photo",
        "url": "https://pbs.twimg.com/media/HLLz0FSa0AAYMFg.jpg",
        "width": 2048
      },
      {
        "height": 2048,
        "media_key": "3_2067983255002071040",
        "public_metrics": {},
        "type": "photo",
        "url": "https://pbs.twimg.com/media/HLLz0FPawAAN4hU.jpg",
        "width": 1536
      },
      {
        "height": 2048,
        "media_key": "3_2067983255018856448",
        "public_metrics": {},
        "type": "photo",
        "url": "https://pbs.twimg.com/media/HLLz0FTa4AAkeGa.jpg",
        "width": 1536
      }
    ],
    "tweets": [
      {
        "article": {},
        "attachments": {},
        "author_id": "1738375202168532992",
        "conversation_id": "2067983284316082317",
        "created_at": "2026-06-19T15:06:19.000Z",
        "edit_controls": {
          "editable_until": "2026-06-19T16:06:19.000Z",
          "edits_remaining": 5,
          "is_edit_eligible": false
        },
        "edit_history_tweet_ids": [
          "2067987345509605862"
        ],
        "entities": {
          "mentions": [
            {
              "end": 13,
              "id": "1991795014163382272",
              "start": 0,
              "username": "fortearsidie"
            }
          ]
        },
        "geo": {},
        "id": "2067987345509605862",
        "in_reply_to_user_id": "1991795014163382272",
        "lang": "zh",
        "note_tweet": {
          "entities": {}
        },
        "possibly_sensitive": false,
        "public_metrics": {
          "bookmark_count": 0,
          "impression_count": 0,
          "like_count": 0,
          "quote_count": 0,
          "reply_count": 0,
          "retweet_count": 0
        },
        "referenced_tweets": [
          {
            "id": "2067983284316082317",
            "type": "replied_to"
          }
        ],
        "reply_settings": "everyone",
        "text": "@fortearsidie 哦！！！！我也想去wwww人多吗！"
      },
      {
        "article": {},
        "attachments": {
          "media_keys": [
            "3_2067983255014658048",
            "3_2067983255002071040",
            "3_2067983255018856448"
          ]
        },
        "author_id": "1991795014163382272",
        "conversation_id": "2067983284316082317",
        "created_at": "2026-06-19T14:50:10.000Z",
        "edit_controls": {
          "editable_until": "2026-06-19T15:50:10.000Z",
          "edits_remaining": 5,
          "is_edit_eligible": true
        },
        "edit_history_tweet_ids": [
          "2067983284316082317"
        ],
        "entities": {
          "urls": [
            {
              "display_url": "pic.x.com/9bRi7BnBIL",
              "end": 32,
              "expanded_url": "https://x.com/fortearsidie/status/2067983284316082317/photo/1",
              "media_key": "3_2067983255014658048",
              "start": 9,
              "url": "https://t.co/9bRi7BnBIL"
            },
            {
              "display_url": "pic.x.com/9bRi7BnBIL",
              "end": 32,
              "expanded_url": "https://x.com/fortearsidie/status/2067983284316082317/photo/1",
              "media_key": "3_2067983255002071040",
              "start": 9,
              "url": "https://t.co/9bRi7BnBIL"
            },
            {
              "display_url": "pic.x.com/9bRi7BnBIL",
              "end": 32,
              "expanded_url": "https://x.com/fortearsidie/status/2067983284316082317/photo/1",
              "media_key": "3_2067983255018856448",
              "start": 9,
              "url": "https://t.co/9bRi7BnBIL"
            }
          ]
        },
        "geo": {},
        "id": "2067983284316082317",
        "lang": "zh",
        "note_tweet": {
          "entities": {}
        },
        "possibly_sensitive": false,
        "public_metrics": {
          "bookmark_count": 0,
          "impression_count": 23,
          "like_count": 4,
          "quote_count": 0,
          "reply_count": 1,
          "retweet_count": 0
        },
        "reply_settings": "everyone",
        "text": "已线下真实超天酱 https://t.co/9bRi7BnBIL"
      }
    ],
    "users": [
      {
        "created_at": "2023-12-23T01:45:30.000Z",
        "description": "叫我丸子就好",
        "id": "1738375202168532992",
        "name": "マルコ",
        "pinned_tweet_id": "2038194838785732817",
        "profile_image_url": "https://pbs.twimg.com/profile_images/2025519980977270784/8ZuZMmmz_normal.jpg",
        "protected": false,
        "public_metrics": {
          "followers_count": 331,
          "following_count": 331,
          "like_count": 19819,
          "listed_count": 0,
          "media_count": 538,
          "tweet_count": 4325
        },
        "url": "",
        "username": "Wanzi5450",
        "verified": false
      },
      {
        "created_at": "2025-11-21T09:05:27.000Z",
        "description": "可以叫我Eri｜Male｜双性浪漫倾向无性恋｜友LGBTQ+\n碎碎念｜大龄社畜｜ISFP｜有对象｜欢迎互fo\nBFF：@hongdounuomi\n“我们彻夜飞旋，直至没入火焰。”",
        "entities": {
          "description": {
            "mentions": [
              {
                "end": 72,
                "start": 59,
                "username": "hongdounuomi"
              }
            ]
          }
        },
        "id": "1991795014163382272",
        "location": "    The Kingdom of overdose",
        "name": "为泪舍己",
        "pinned_tweet_id": "2054249080063504423",
        "profile_image_url": "https://pbs.twimg.com/profile_images/2053154412919721985/J6EwJycm_normal.jpg",
        "protected": false,
        "public_metrics": {
          "followers_count": 275,
          "following_count": 488,
          "like_count": 8261,
          "listed_count": 0,
          "media_count": 48,
          "tweet_count": 214
        },
        "url": "",
        "username": "fortearsidie",
        "verified": true
      }
    ]
  }
}