{
  "data": {
    "article": {},
    "attachments": {
      "media_keys": [
        "3_2031316046477697025"
      ]
    },
    "author_id": "1738375202168532992",
    "context_annotations": [
      {
        "domain": {
          "description": "Categories within Brand Verticals that narrow down the scope of Brands",
          "id": "46",
          "name": "Business Taxonomy"
        },
        "entity": {
          "description": "Brands, companies, advertisers and every non-person handle with the profit intent and related to foods & beverages such as snacks, soft drinks, beers.",
          "id": "1557696888568045569",
          "name": "Food & Beverage Business"
        }
      },
      {
        "domain": {
          "description": "A taxonomy of user interests. ",
          "id": "131",
          "name": "Unified Twitter Taxonomy"
        },
        "entity": {
          "description": "Drinks",
          "id": "834828264786898945",
          "name": "Drinks"
        }
      },
      {
        "domain": {
          "description": "A taxonomy of user interests. ",
          "id": "131",
          "name": "Unified Twitter Taxonomy"
        },
        "entity": {
          "description": "Milk",
          "id": "850419241790472192",
          "name": "Milk"
        }
      },
      {
        "domain": {
          "description": "Topics about food, like Donuts or Brunch",
          "id": "152",
          "name": "Food"
        },
        "entity": {
          "description": "Milk",
          "id": "850419241790472192",
          "name": "Milk"
        }
      },
      {
        "domain": {
          "description": "A product taxonomy for labeling categories of products. ",
          "id": "173",
          "name": "Product Taxonomy"
        },
        "entity": {
          "description": "Milk",
          "id": "850419241790472192",
          "name": "Milk"
        }
      }
    ],
    "conversation_id": "2031316053008204072",
    "created_at": "2026-03-10T10:27:41.000Z",
    "edit_controls": {
      "editable_until": "2026-03-10T11:27:41.000Z",
      "edits_remaining": 5,
      "is_edit_eligible": true
    },
    "edit_history_tweet_ids": [
      "2031316053008204072"
    ],
    "entities": {
      "urls": [
        {
          "display_url": "pic.x.com/iAQqgetRJJ",
          "end": 53,
          "expanded_url": "https://x.com/Wanzi5450/status/2031316053008204072/photo/1",
          "media_key": "3_2031316046477697025",
          "start": 30,
          "url": "https://t.co/iAQqgetRJJ"
        }
      ]
    },
    "geo": {},
    "id": "2031316053008204072",
    "lang": "zh",
    "note_tweet": {
      "entities": {}
    },
    "possibly_sensitive": false,
    "public_metrics": {
      "bookmark_count": 0,
      "impression_count": 0,
      "like_count": 0,
      "quote_count": 0,
      "reply_count": 0,
      "retweet_count": 0
    },
    "reply_settings": "everyone",
    "text": "好喝好喝好喝好喝好喝好喝快去喝快去喝\n喜茶 荞麦龙井牛乳茶 https://t.co/iAQqgetRJJ"
  },
  "includes": {
    "media": [
      {
        "height": 2048,
        "media_key": "3_2031316046477697025",
        "public_metrics": {},
        "type": "photo",
        "url": "https://pbs.twimg.com/media/HDCvLpDaoAE0XvG.jpg",
        "width": 1536
      }
    ],
    "tweets": [
      {
        "article": {},
        "attachments": {
          "media_keys": [
            "3_2031316046477697025"
          ]
        },
        "author_id": "1738375202168532992",
        "context_annotations": [
          {
            "domain": {
              "description": "Categories within Brand Verticals that narrow down the scope of Brands",
              "id": "46",
              "name": "Business Taxonomy"
            },
            "entity": {
              "description": "Brands, companies, advertisers and every non-person handle with the profit intent and related to foods & beverages such as snacks, soft drinks, beers.",
              "id": "1557696888568045569",
              "name": "Food & Beverage Business"
            }
          },
          {
            "domain": {
              "description": "A taxonomy of user interests. ",
              "id": "131",
              "name": "Unified Twitter Taxonomy"
            },
            "entity": {
              "description": "Drinks",
              "id": "834828264786898945",
              "name": "Drinks"
            }
          },
          {
            "domain": {
              "description": "A taxonomy of user interests. ",
              "id": "131",
              "name": "Unified Twitter Taxonomy"
            },
            "entity": {
              "description": "Milk",
              "id": "850419241790472192",
              "name": "Milk"
            }
          },
          {
            "domain": {
              "description": "Topics about food, like Donuts or Brunch",
              "id": "152",
              "name": "Food"
            },
            "entity": {
              "description": "Milk",
              "id": "850419241790472192",
              "name": "Milk"
            }
          },
          {
            "domain": {
              "description": "A product taxonomy for labeling categories of products. ",
              "id": "173",
              "name": "Product Taxonomy"
            },
            "entity": {
              "description": "Milk",
              "id": "850419241790472192",
              "name": "Milk"
            }
          }
        ],
        "conversation_id": "2031316053008204072",
        "created_at": "2026-03-10T10:27:41.000Z",
        "edit_controls": {
          "editable_until": "2026-03-10T11:27:41.000Z",
          "edits_remaining": 5,
          "is_edit_eligible": true
        },
        "edit_history_tweet_ids": [
          "2031316053008204072"
        ],
        "entities": {
          "urls": [
            {
              "display_url": "pic.x.com/iAQqgetRJJ",
              "end": 53,
              "expanded_url": "https://x.com/Wanzi5450/status/2031316053008204072/photo/1",
              "media_key": "3_2031316046477697025",
              "start": 30,
              "url": "https://t.co/iAQqgetRJJ"
            }
          ]
        },
        "geo": {},
        "id": "2031316053008204072",
        "lang": "zh",
        "note_tweet": {
          "entities": {}
        },
        "possibly_sensitive": false,
        "public_metrics": {
          "bookmark_count": 0,
          "impression_count": 0,
          "like_count": 0,
          "quote_count": 0,
          "reply_count": 0,
          "retweet_count": 0
        },
        "reply_settings": "everyone",
        "text": "好喝好喝好喝好喝好喝好喝快去喝快去喝\n喜茶 荞麦龙井牛乳茶 https://t.co/iAQqgetRJJ"
      }
    ],
    "users": [
      {
        "created_at": "2023-12-23T01:45:30.000Z",
        "description": "",
        "id": "1738375202168532992",
        "name": "マルコ",
        "profile_image_url": "https://pbs.twimg.com/profile_images/2025519980977270784/8ZuZMmmz_normal.jpg",
        "protected": false,
        "public_metrics": {
          "followers_count": 30,
          "following_count": 230,
          "like_count": 8841,
          "listed_count": 0,
          "media_count": 323,
          "tweet_count": 1944
        },
        "username": "Wanzi5450",
        "verified": false
      }
    ]
  }
}