{
  "data": {
    "article": {},
    "attachments": {},
    "author_id": "1738375202168532992",
    "conversation_id": "2063488270915580123",
    "created_at": "2026-06-07T05:08:36.000Z",
    "edit_controls": {
      "editable_until": "2026-06-07T06:08:36.000Z",
      "edits_remaining": 5,
      "is_edit_eligible": true
    },
    "edit_history_tweet_ids": [
      "2063488270915580123"
    ],
    "entities": {},
    "geo": {},
    "id": "2063488270915580123",
    "lang": "zh",
    "note_tweet": {
      "entities": {}
    },
    "possibly_sensitive": false,
    "public_metrics": {
      "bookmark_count": 0,
      "impression_count": 0,
      "like_count": 0,
      "quote_count": 0,
      "reply_count": 0,
      "retweet_count": 0
    },
    "reply_settings": "everyone",
    "text": "虽然没有抑郁但是今天在还债前几天吃的醋汁药反跳和透支的体力以至于我在高考考场上坐着都略微喘不过气走路更是浑身没力啊））醋汁药大人我错了舞萌大人我也错了✋🏻😭🤚🏻今明两天绝对不打说到做到嗯。\n*请勿在此条po文下评论高考加油，极度反感，感谢。但可以说舞萌加油(^-^)"
  },
  "includes": {
    "tweets": [
      {
        "article": {},
        "attachments": {},
        "author_id": "1738375202168532992",
        "conversation_id": "2063488270915580123",
        "created_at": "2026-06-07T05:08:36.000Z",
        "edit_controls": {
          "editable_until": "2026-06-07T06:08:36.000Z",
          "edits_remaining": 5,
          "is_edit_eligible": true
        },
        "edit_history_tweet_ids": [
          "2063488270915580123"
        ],
        "entities": {},
        "geo": {},
        "id": "2063488270915580123",
        "lang": "zh",
        "note_tweet": {
          "entities": {}
        },
        "possibly_sensitive": false,
        "public_metrics": {
          "bookmark_count": 0,
          "impression_count": 0,
          "like_count": 0,
          "quote_count": 0,
          "reply_count": 0,
          "retweet_count": 0
        },
        "reply_settings": "everyone",
        "text": "虽然没有抑郁但是今天在还债前几天吃的醋汁药反跳和透支的体力以至于我在高考考场上坐着都略微喘不过气走路更是浑身没力啊））醋汁药大人我错了舞萌大人我也错了✋🏻😭🤚🏻今明两天绝对不打说到做到嗯。\n*请勿在此条po文下评论高考加油，极度反感，感谢。但可以说舞萌加油(^-^)"
      }
    ],
    "users": [
      {
        "created_at": "2023-12-23T01:45:30.000Z",
        "description": "叫我丸子就好",
        "id": "1738375202168532992",
        "name": "マルコ",
        "pinned_tweet_id": "2038194838785732817",
        "profile_image_url": "https://pbs.twimg.com/profile_images/2025519980977270784/8ZuZMmmz_normal.jpg",
        "protected": false,
        "public_metrics": {
          "followers_count": 308,
          "following_count": 318,
          "like_count": 18524,
          "listed_count": 0,
          "media_count": 520,
          "tweet_count": 4161
        },
        "username": "Wanzi5450",
        "verified": false
      }
    ]
  }
}