{
  "data": {
    "article": {},
    "attachments": {},
    "author_id": "1738375202168532992",
    "conversation_id": "2043007527798083800",
    "created_at": "2026-04-11T17:45:25.000Z",
    "edit_controls": {
      "editable_until": "2026-04-11T18:45:25.000Z",
      "edits_remaining": 5,
      "is_edit_eligible": false
    },
    "edit_history_tweet_ids": [
      "2043022621898625435"
    ],
    "entities": {
      "mentions": [
        {
          "end": 13,
          "id": "1854817785140199428",
          "start": 0,
          "username": "rainnnnn0423"
        }
      ]
    },
    "geo": {},
    "id": "2043022621898625435",
    "in_reply_to_user_id": "1854817785140199428",
    "lang": "ja",
    "note_tweet": {
      "entities": {}
    },
    "possibly_sensitive": false,
    "public_metrics": {
      "bookmark_count": 0,
      "impression_count": 0,
      "like_count": 0,
      "quote_count": 0,
      "reply_count": 0,
      "retweet_count": 0
    },
    "referenced_tweets": [
      {
        "id": "2043007527798083800",
        "type": "replied_to"
      }
    ],
    "reply_settings": "everyone",
    "text": "@rainnnnn0423 莫名看着好像老番茄"
  },
  "errors": [
    {
      "detail": "Sorry, you are not authorized to see the Tweet with referenced_tweets.id: [2043007527798083800].",
      "parameter": "referenced_tweets.id",
      "resource_id": "2043007527798083800",
      "resource_type": "tweet",
      "section": "includes",
      "title": "Authorization Error",
      "type": "https://api.twitter.com/2/problems/not-authorized-for-resource",
      "value": "2043007527798083800"
    }
  ],
  "includes": {
    "tweets": [
      {
        "article": {},
        "attachments": {},
        "author_id": "1738375202168532992",
        "conversation_id": "2043007527798083800",
        "created_at": "2026-04-11T17:45:25.000Z",
        "edit_controls": {
          "editable_until": "2026-04-11T18:45:25.000Z",
          "edits_remaining": 5,
          "is_edit_eligible": false
        },
        "edit_history_tweet_ids": [
          "2043022621898625435"
        ],
        "entities": {
          "mentions": [
            {
              "end": 13,
              "id": "1854817785140199428",
              "start": 0,
              "username": "rainnnnn0423"
            }
          ]
        },
        "geo": {},
        "id": "2043022621898625435",
        "in_reply_to_user_id": "1854817785140199428",
        "lang": "ja",
        "note_tweet": {
          "entities": {}
        },
        "possibly_sensitive": false,
        "public_metrics": {
          "bookmark_count": 0,
          "impression_count": 0,
          "like_count": 0,
          "quote_count": 0,
          "reply_count": 0,
          "retweet_count": 0
        },
        "referenced_tweets": [
          {
            "id": "2043007527798083800",
            "type": "replied_to"
          }
        ],
        "reply_settings": "everyone",
        "text": "@rainnnnn0423 莫名看着好像老番茄"
      }
    ],
    "users": [
      {
        "created_at": "2023-12-23T01:45:30.000Z",
        "description": "叫我丸子就好",
        "id": "1738375202168532992",
        "name": "マルコ",
        "pinned_tweet_id": "2042100348303896775",
        "profile_image_url": "https://pbs.twimg.com/profile_images/2025519980977270784/8ZuZMmmz_normal.jpg",
        "protected": false,
        "public_metrics": {
          "followers_count": 159,
          "following_count": 264,
          "like_count": 11671,
          "listed_count": 0,
          "media_count": 452,
          "tweet_count": 3123
        },
        "username": "Wanzi5450",
        "verified": false
      },
      {
        "created_at": "2024-11-08T09:26:50.000Z",
        "description": "自言自语bot|胡言乱语的赛博日记本🗑|各种敏感发言请注意|一般路过女高|我不是键政区吗怎么成⌚姐了|粉蛆滚 正主@oolongisgood321 好诡秘@si_an_1122 第二人格@634livinlimbo 特级野狗@404ADHD_DOG🚪88 我不吸毒谢谢 互fo请私信 暂时锁一段时间",
        "entities": {
          "description": {
            "mentions": [
              {
                "end": 73,
                "start": 57,
                "username": "oolongisgood321"
              },
              {
                "end": 88,
                "start": 77,
                "username": "si_an_1122"
              },
              {
                "end": 107,
                "start": 93,
                "username": "634livinlimbo"
              },
              {
                "end": 124,
                "start": 112,
                "username": "404ADHD_DOG"
              }
            ]
          }
        },
        "id": "1854817785140199428",
        "location": "避雨小屋",
        "name": "气态雨",
        "pinned_tweet_id": "2040862365714129402",
        "profile_image_url": "https://pbs.twimg.com/profile_images/1987543107173228544/Vy7r5VfA_normal.jpg",
        "protected": true,
        "public_metrics": {
          "followers_count": 335,
          "following_count": 648,
          "like_count": 5454,
          "listed_count": 4,
          "media_count": 344,
          "tweet_count": 4717
        },
        "username": "rainnnnn0423",
        "verified": false
      }
    ]
  }
}